{
  "title": "小学语文统编版一年级下册",
  "xueduan": "小学",
  "nianji": "一年级",
  "xueke": "语文",
  "banben": "统编版",
  "ceci": "下册",
  "is_new": false,
  "chapters": [
    {
      "title": "识字",
      "level": 1,
      "index": 1,
      "children": [
        {
          "title": "1 春夏秋冬",
          "level": 2,
          "index": 1
        },
        {
          "title": "2 姓氏歌",
          "level": 2,
          "index": 2
        },
        {
          "title": "3 小青蛙",
          "level": 2,
          "index": 3
        },
        {
          "title": "4 猜字谜",
          "level": 2,
          "index": 4
        },
        {
          "title": "口语交际：听故事，讲故事",
          "level": 2,
          "index": 5
        },
        {
          "title": "语文园地一",
          "level": 2,
          "index": 6,
          "children": [
            {
              "title": "识字加油站+书写提示+日积月累",
              "level": 3,
              "index": 1
            },
            {
              "title": "字词句运用",
              "level": 3,
              "index": 2
            },
            {
              "title": "和大人一起读：谁和谁好",
              "level": 3,
              "index": 3
            },
            {
              "title": "单元拓展",
              "level": 3,
              "index": 4
            }
          ]
        },
        {
          "title": "快乐读书吧：读读童谣和儿歌",
          "level": 2,
          "index": 7
        }
      ]
    },
    {
      "title": "课文",
      "level": 1,
      "index": 2,
      "children": [
        {
          "title": "1 吃水不忘挖井人",
          "level": 2,
          "index": 1
        },
        {
          "title": "2 我多想去看看",
          "level": 2,
          "index": 2
        },
        {
          "title": "3 一个接一个",
          "level": 2,
          "index": 3
        },
        {
          "title": "3 四个太阳",
          "level": 2,
          "index": 4
        },
        {
          "title": "语文园地二",
          "level": 2,
          "index": 5,
          "children": [
            {
              "title": "识字加油站+字词句运用",
              "level": 3,
              "index": 1
            },
            {
              "title": "展示台+日积月累",
              "level": 3,
              "index": 2
            },
            {
              "title": "和大人一起读：阳光",
              "level": 3,
              "index": 3
            },
            {
              "title": "单元拓展",
              "level": 3,
              "index": 4
            }
          ]
        },
        {
          "title": "4小公鸡和小鸭子",
          "level": 2,
          "index": 6
        },
        {
          "title": "5 树和喜鹊",
          "level": 2,
          "index": 7
        },
        {
          "title": "6 怎么都快乐",
          "level": 2,
          "index": 8
        },
        {
          "title": "口语交际：请你帮个忙",
          "level": 2,
          "index": 9
        },
        {
          "title": "语文园地三",
          "level": 2,
          "index": 10,
          "children": [
            {
              "title": "查字典",
              "level": 3,
              "index": 1
            },
            {
              "title": "日积月累+和大人一起读：胖乎乎的小手",
              "level": 3,
              "index": 2
            },
            {
              "title": "单元拓展",
              "level": 3,
              "index": 3
            }
          ]
        },
        {
          "title": "7 静夜思",
          "level": 2,
          "index": 11
        },
        {
          "title": "8 夜色",
          "level": 2,
          "index": 12
        },
        {
          "title": "9 端午粽",
          "level": 2,
          "index": 13
        },
        {
          "title": "10 彩虹",
          "level": 2,
          "index": 14
        },
        {
          "title": "语文园地四",
          "level": 2,
          "index": 15,
          "children": [
            {
              "title": "识字加油站+字词句运用",
              "level": 3,
              "index": 1
            },
            {
              "title": "书写提示+日积月累",
              "level": 3,
              "index": 2
            },
            {
              "title": "和大人一起读：妞妞赶牛",
              "level": 3,
              "index": 3
            },
            {
              "title": "单元拓展",
              "level": 3,
              "index": 4
            }
          ]
        }
      ]
    },
    {
      "title": "识字",
      "level": 1,
      "index": 3,
      "children": [
        {
          "title": "5 动物儿歌",
          "level": 2,
          "index": 1
        },
        {
          "title": "6 古对今",
          "level": 2,
          "index": 2
        },
        {
          "title": "7 操场上",
          "level": 2,
          "index": 3
        },
        {
          "title": "8 人之初",
          "level": 2,
          "index": 4
        },
        {
          "title": "口语交际：打电话",
          "level": 2,
          "index": 5
        },
        {
          "title": "语文园地五",
          "level": 2,
          "index": 6,
          "children": [
            {
              "title": "识字加油站+我的发现",
              "level": 3,
              "index": 1
            },
            {
              "title": "字词句运用+日积月累",
              "level": 3,
              "index": 2
            },
            {
              "title": "和大人一起读：狐狸和乌鸦",
              "level": 3,
              "index": 3
            },
            {
              "title": "单元拓展",
              "level": 3,
              "index": 4
            }
          ]
        }
      ]
    },
    {
      "title": "课文",
      "level": 1,
      "index": 4,
      "children": [
        {
          "title": "11 古诗二首",
          "level": 2,
          "index": 1,
          "children": [
            {
              "title": "池上",
              "level": 3,
              "index": 1
            },
            {
              "title": "小池",
              "level": 3,
              "index": 2
            }
          ]
        },
        {
          "title": "12 荷叶圆圆",
          "level": 2,
          "index": 2
        },
        {
          "title": "13 要下雨了",
          "level": 2,
          "index": 3
        },
        {
          "title": "语文园地六",
          "level": 2,
          "index": 4,
          "children": [
            {
              "title": "识字加油站+展示台",
              "level": 3,
              "index": 1
            },
            {
              "title": "字词句运用+日积月累",
              "level": 3,
              "index": 2
            },
            {
              "title": "和大人一起读：夏夜多美",
              "level": 3,
              "index": 3
            },
            {
              "title": "单元拓展",
              "level": 3,
              "index": 4
            }
          ]
        },
        {
          "title": "14 文具的家",
          "level": 2,
          "index": 5
        },
        {
          "title": "15 一分钟",
          "level": 2,
          "index": 6
        },
        {
          "title": "16 动物王国开大会",
          "level": 2,
          "index": 7
        },
        {
          "title": "17 小猴子下山",
          "level": 2,
          "index": 8
        },
        {
          "title": "口语交际：一起做游戏",
          "level": 2,
          "index": 9
        },
        {
          "title": "语文园地七",
          "level": 2,
          "index": 10,
          "children": [
            {
              "title": "识字加油站+字词句运用",
              "level": 3,
              "index": 1
            },
            {
              "title": "书写提示+日积月累",
              "level": 3,
              "index": 2
            },
            {
              "title": "和大人一起读：孙悟空打妖怪",
              "level": 3,
              "index": 3
            },
            {
              "title": "单元拓展",
              "level": 3,
              "index": 4
            }
          ]
        },
        {
          "title": "18 棉花姑娘",
          "level": 2,
          "index": 11
        },
        {
          "title": "19 咕咚",
          "level": 2,
          "index": 12
        },
        {
          "title": "20 小壁虎借尾巴",
          "level": 2,
          "index": 13
        },
        {
          "title": "语文园地八",
          "level": 2,
          "index": 14,
          "children": [
            {
              "title": "识字加油站+我的发现",
              "level": 3,
              "index": 1
            },
            {
              "title": "字词句运用+日积月累",
              "level": 3,
              "index": 2
            },
            {
              "title": "和大人一起读：三只白鹤",
              "level": 3,
              "index": 3
            },
            {
              "title": "和大人一起读：小熊住山洞",
              "level": 3,
              "index": 4
            },
            {
              "title": "单元拓展",
              "level": 3,
              "index": 5
            }
          ]
        }
      ]
    },
    {
      "title": "识字表",
      "level": 1,
      "index": 5
    },
    {
      "title": "写字表",
      "level": 1,
      "index": 6
    },
    {
      "title": "常用偏旁名称表",
      "level": 1,
      "index": 7
    }
  ]
}