{
  "title": "初中地理晋教版八年级上册",
  "xueduan": "初中",
  "nianji": "八年级",
  "xueke": "地理",
  "banben": "晋教版",
  "ceci": "上册",
  "is_new": false,
  "chapters": [
    {
      "title": "第一章 疆域和人口——从世界看中国",
      "level": 1,
      "index": 1,
      "children": [
        {
          "title": "1.1 辽阔的国土",
          "level": 2,
          "index": 1
        },
        {
          "title": "1.2 众多的人口",
          "level": 2,
          "index": 2
        }
      ]
    },
    {
      "title": "第二章 自然环境——我们赖以生存的基本条件",
      "level": 1,
      "index": 2,
      "children": [
        {
          "title": "2.1 千姿百态的地表形态",
          "level": 2,
          "index": 1
        },
        {
          "title": "2.2 复杂多样的气候",
          "level": 2,
          "index": 2
        },
        {
          "title": "2.3 数以万计的河流",
          "level": 2,
          "index": 3
        }
      ]
    },
    {
      "title": "第三章 自然资源——我国生存和发展的物质基础",
      "level": 1,
      "index": 3,
      "children": [
        {
          "title": "3.1 丰富的自然资源",
          "level": 2,
          "index": 1
        },
        {
          "title": "3.2 有限的耕地资源",
          "level": 2,
          "index": 2
        },
        {
          "title": "3.3 紧缺的水资源",
          "level": 2,
          "index": 3
        }
      ]
    },
    {
      "title": "第四章 经济发展——强国富民之路",
      "level": 1,
      "index": 4,
      "children": [
        {
          "title": "4.1 稳步增长的农业",
          "level": 2,
          "index": 1
        },
        {
          "title": "4.2 快速发展的工业",
          "level": 2,
          "index": 2
        },
        {
          "title": "4.3 腾飞的交通运输业",
          "level": 2,
          "index": 3
        }
      ]
    }
  ]
}