{
  "title": "新教材-小学（五·四学制）科学青岛版一年级上册",
  "xueduan": "小学（五•四学制）",
  "nianji": "一年级",
  "xueke": "科学",
  "banben": "青岛版",
  "ceci": "上册",
  "is_new": true,
  "chapters": [
    {
      "title": "第一单元 走进科学课",
      "level": 1,
      "index": 1,
      "children": [
        {
          "title": "1.吹泡泡",
          "level": 2,
          "index": 1
        },
        {
          "title": "2.把它们立起来",
          "level": 2,
          "index": 2
        },
        {
          "title": "3.我的“小问号”",
          "level": 2,
          "index": 3
        }
      ]
    },
    {
      "title": "第二单元 我们怎样观察",
      "level": 1,
      "index": 2,
      "children": [
        {
          "title": "4.看一看",
          "level": 2,
          "index": 1
        },
        {
          "title": "5.听一听",
          "level": 2,
          "index": 2
        },
        {
          "title": "6.摸一摸",
          "level": 2,
          "index": 3
        },
        {
          "title": "7.闻和尝",
          "level": 2,
          "index": 4
        },
        {
          "title": "8.比一比",
          "level": 2,
          "index": 5
        },
        {
          "title": "9.给树做“名片”",
          "level": 2,
          "index": 6
        }
      ]
    },
    {
      "title": "第三单元 玩中学",
      "level": 1,
      "index": 3,
      "children": [
        {
          "title": "10.玩小车",
          "level": 2,
          "index": 1
        },
        {
          "title": "11.玩彩泥",
          "level": 2,
          "index": 2
        },
        {
          "title": "12.玩磁铁",
          "level": 2,
          "index": 3
        },
        {
          "title": "13.做纸蜻蜓",
          "level": 2,
          "index": 4
        }
      ]
    },
    {
      "title": "第四单元 使用工具",
      "level": 1,
      "index": 4,
      "children": [
        {
          "title": "14.认识放大镜",
          "level": 2,
          "index": 1
        },
        {
          "title": "15.研究削笔刀",
          "level": 2,
          "index": 2
        },
        {
          "title": "16.修理玩具",
          "level": 2,
          "index": 3
        }
      ]
    }
  ]
}