{
  "title": "小学科学冀人版五年级下册",
  "xueduan": "小学",
  "nianji": "五年级",
  "xueke": "科学",
  "banben": "冀人版",
  "ceci": "下册",
  "is_new": false,
  "chapters": [
    {
      "title": "第1单元 水的三态变化",
      "level": 1,
      "index": 1,
      "children": [
        {
          "title": "1 水到哪里去了",
          "level": 2,
          "index": 1
        },
        {
          "title": "2 小水珠从哪里来",
          "level": 2,
          "index": 2
        },
        {
          "title": "3 水的状态变化与什么有关",
          "level": 2,
          "index": 3
        }
      ]
    },
    {
      "title": "第2单元 水循环",
      "level": 1,
      "index": 2,
      "children": [
        {
          "title": "4 露和霜",
          "level": 2,
          "index": 1
        },
        {
          "title": "5 雾和云",
          "level": 2,
          "index": 2
        },
        {
          "title": "6 雨和雪",
          "level": 2,
          "index": 3
        },
        {
          "title": "7 地球上的水循环",
          "level": 2,
          "index": 4
        }
      ]
    },
    {
      "title": "第3单元 地表缓慢变化",
      "level": 1,
      "index": 3,
      "children": [
        {
          "title": "8 雨水侵蚀地表",
          "level": 2,
          "index": 1
        },
        {
          "title": "9 沙洲的形成",
          "level": 2,
          "index": 2
        },
        {
          "title": "10 人类与地表环境",
          "level": 2,
          "index": 3
        }
      ]
    },
    {
      "title": "第4单元 多样的生物",
      "level": 1,
      "index": 4,
      "children": [
        {
          "title": "11 种类繁多的植物",
          "level": 2,
          "index": 1
        },
        {
          "title": "12 观察细胞",
          "level": 2,
          "index": 2
        },
        {
          "title": "13 看不见的微生物",
          "level": 2,
          "index": 3
        },
        {
          "title": "14 看得见的微生物",
          "level": 2,
          "index": 4
        },
        {
          "title": "15 发霉和防霉",
          "level": 2,
          "index": 5
        }
      ]
    },
    {
      "title": "第5单元 简单机械",
      "level": 1,
      "index": 5,
      "children": [
        {
          "title": "16 怎样才省力",
          "level": 2,
          "index": 1
        },
        {
          "title": "17 撬杠的学问",
          "level": 2,
          "index": 2
        },
        {
          "title": "18 轮轴的秘密",
          "level": 2,
          "index": 3
        },
        {
          "title": "19 滑轮的作用",
          "level": 2,
          "index": 4
        },
        {
          "title": "20 斜面的作用",
          "level": 2,
          "index": 5
        },
        {
          "title": "21 自行车",
          "level": 2,
          "index": 6
        }
      ]
    },
    {
      "title": "第6单元 科学擂台——机器模型",
      "level": 1,
      "index": 6,
      "children": [
        {
          "title": "22 科学擂台——机器模型大比拼（一）",
          "level": 2,
          "index": 1
        },
        {
          "title": "23 科学擂台——机器模型大比拼（二）",
          "level": 2,
          "index": 2
        },
        {
          "title": "24 科学擂台——机器模型大比拼（三）",
          "level": 2,
          "index": 3
        }
      ]
    }
  ]
}