{
  "title": "高中音乐粤教花城版必修2 歌唱",
  "xueduan": "高中",
  "nianji": "",
  "xueke": "音乐",
  "banben": "粤教花城版",
  "ceci": "必修2 歌唱",
  "is_new": false,
  "chapters": [
    {
      "title": "第一单元 美妙的人声",
      "level": 1,
      "index": 1,
      "children": [
        {
          "title": "第1节 神奇的“乐器”",
          "level": 2,
          "index": 1
        },
        {
          "title": "第2节 人声的种类",
          "level": 2,
          "index": 2
        },
        {
          "title": "第3节 演唱的形式",
          "level": 2,
          "index": 3
        },
        {
          "title": "第4节 唱法的区分",
          "level": 2,
          "index": 4
        }
      ]
    },
    {
      "title": "第二单元 歌唱的奥妙（一）",
      "level": 1,
      "index": 2,
      "children": [
        {
          "title": "第1节 歌唱的状态",
          "level": 2,
          "index": 1
        },
        {
          "title": "第2节 歌唱的呼吸",
          "level": 2,
          "index": 2
        },
        {
          "title": "第3节 歌唱的共鸣",
          "level": 2,
          "index": 3
        },
        {
          "title": "第4节 歌唱的咬字与吐字",
          "level": 2,
          "index": 4
        },
        {
          "title": "第5节 歌唱的语调、语气、语势",
          "level": 2,
          "index": 5
        }
      ]
    },
    {
      "title": "第三单元 歌唱的奥妙（二）",
      "level": 1,
      "index": 3,
      "children": [
        {
          "title": "第1节 音色与情感",
          "level": 2,
          "index": 1
        },
        {
          "title": "第2节 速度、力度、情绪",
          "level": 2,
          "index": 2
        },
        {
          "title": "第3节 润腔与韵味",
          "level": 2,
          "index": 3
        },
        {
          "title": "第4节 歌唱形象与舞台表现",
          "level": 2,
          "index": 4
        }
      ]
    },
    {
      "title": "第四单元 重唱情趣",
      "level": 1,
      "index": 4,
      "children": [
        {
          "title": "第1节 二重唱",
          "level": 2,
          "index": 1
        },
        {
          "title": "第2节 三重唱",
          "level": 2,
          "index": 2
        },
        {
          "title": "第3节 多声组合",
          "level": 2,
          "index": 3
        },
        {
          "title": "第4节 人声乐团",
          "level": 2,
          "index": 4
        }
      ]
    },
    {
      "title": "第五单元 合唱魅力（一）",
      "level": 1,
      "index": 5,
      "children": [
        {
          "title": "第1节 多声的艺术",
          "level": 2,
          "index": 1
        },
        {
          "title": "第2节 中国合唱的魅力",
          "level": 2,
          "index": 2
        },
        {
          "title": "第3节 世界合唱的精华",
          "level": 2,
          "index": 3
        }
      ]
    },
    {
      "title": "第六单元 合唱魅力（二）",
      "level": 1,
      "index": 6,
      "children": [
        {
          "title": "第1节 合唱的多维空间",
          "level": 2,
          "index": 1
        },
        {
          "title": "第2节 合唱的声音色彩",
          "level": 2,
          "index": 2
        },
        {
          "title": "第3节 指挥的语汇",
          "level": 2,
          "index": 3
        }
      ]
    }
  ]
}