{
  "title": "初中道德与法治统编版八年级上册",
  "xueduan": "初中",
  "nianji": "八年级",
  "xueke": "道德与法治",
  "banben": "统编版",
  "ceci": "上册",
  "is_new": false,
  "chapters": [
    {
      "title": "第一单元 走进社会生活",
      "level": 1,
      "index": 1,
      "children": [
        {
          "title": "第一课 丰富的社会生活",
          "level": 2,
          "index": 1,
          "children": [
            {
              "title": "我与社会",
              "level": 3,
              "index": 1
            },
            {
              "title": "在社会中成长",
              "level": 3,
              "index": 2
            }
          ]
        },
        {
          "title": "第二课 网络生活新空间",
          "level": 2,
          "index": 2,
          "children": [
            {
              "title": "网络改变世界",
              "level": 3,
              "index": 1
            },
            {
              "title": "合理利用网络",
              "level": 3,
              "index": 2
            }
          ]
        }
      ]
    },
    {
      "title": "第二单元 遵守社会规则",
      "level": 1,
      "index": 2,
      "children": [
        {
          "title": "第三课 社会生活离不开规则",
          "level": 2,
          "index": 1,
          "children": [
            {
              "title": "维护秩序",
              "level": 3,
              "index": 1
            },
            {
              "title": "遵守规则",
              "level": 3,
              "index": 2
            }
          ]
        },
        {
          "title": "第四课 社会生活讲道德",
          "level": 2,
          "index": 2,
          "children": [
            {
              "title": "尊重他人",
              "level": 3,
              "index": 1
            },
            {
              "title": "以礼待人",
              "level": 3,
              "index": 2
            },
            {
              "title": "诚实守信",
              "level": 3,
              "index": 3
            }
          ]
        },
        {
          "title": "第五课 做守法的公民",
          "level": 2,
          "index": 3,
          "children": [
            {
              "title": "法不可违",
              "level": 3,
              "index": 1
            },
            {
              "title": "预防犯罪",
              "level": 3,
              "index": 2
            },
            {
              "title": "善用法律",
              "level": 3,
              "index": 3
            }
          ]
        }
      ]
    },
    {
      "title": "第三单元 勇担社会责任",
      "level": 1,
      "index": 3,
      "children": [
        {
          "title": "第六课 责任与角色同在",
          "level": 2,
          "index": 1,
          "children": [
            {
              "title": "我对谁负责 谁对我负责",
              "level": 3,
              "index": 1
            },
            {
              "title": "做负责任的人",
              "level": 3,
              "index": 2
            }
          ]
        },
        {
          "title": "第七课 积极奉献社会",
          "level": 2,
          "index": 2,
          "children": [
            {
              "title": "关爱他人",
              "level": 3,
              "index": 1
            },
            {
              "title": "服务社会",
              "level": 3,
              "index": 2
            }
          ]
        }
      ]
    },
    {
      "title": "第四单元 维护国家利益",
      "level": 1,
      "index": 4,
      "children": [
        {
          "title": "第八课 国家利益至上",
          "level": 2,
          "index": 1,
          "children": [
            {
              "title": "国家好 大家才会好",
              "level": 3,
              "index": 1
            },
            {
              "title": "坚持国家利益至上",
              "level": 3,
              "index": 2
            }
          ]
        },
        {
          "title": "第九课 树立总体国家安全观",
          "level": 2,
          "index": 2,
          "children": [
            {
              "title": "认识总体国家安全观",
              "level": 3,
              "index": 1
            },
            {
              "title": "维护国家安全",
              "level": 3,
              "index": 2
            }
          ]
        },
        {
          "title": "第十课 建设美好祖国",
          "level": 2,
          "index": 3,
          "children": [
            {
              "title": "关心国家发展",
              "level": 3,
              "index": 1
            },
            {
              "title": "天下兴亡 匹夫有责",
              "level": 3,
              "index": 2
            }
          ]
        }
      ]
    },
    {
      "title": "专题课",
      "level": 1,
      "index": 5,
      "children": [
        {
          "title": "整体复习一",
          "level": 2,
          "index": 1
        },
        {
          "title": "整体复习二",
          "level": 2,
          "index": 2
        },
        {
          "title": "整体复习三",
          "level": 2,
          "index": 3
        }
      ]
    }
  ]
}