{
  "title": "小学音乐沪教版六年级下册",
  "xueduan": "小学",
  "nianji": "六年级",
  "xueke": "艺术·音乐",
  "banben": "沪教版",
  "ceci": "下册",
  "is_new": false,
  "chapters": [
    {
      "title": "第一单元 山路弯弯",
      "level": 1,
      "index": 1,
      "children": [
        {
          "title": "开心一刻  唱山歌",
          "level": 2,
          "index": 1
        },
        {
          "title": "唱歌  《太阳出来喜洋洋》《山这边，山那边》",
          "level": 2,
          "index": 2
        },
        {
          "title": "聆听  《空山鸟语》《回声》《山童》",
          "level": 2,
          "index": 3
        },
        {
          "title": "编创  山童音乐会",
          "level": 2,
          "index": 4
        }
      ]
    },
    {
      "title": "第二单元 欢乐舞步",
      "level": 1,
      "index": 2,
      "children": [
        {
          "title": "开心一刻  脚铃舞",
          "level": 2,
          "index": 1
        },
        {
          "title": "唱歌  《在一起》《小杜鹃》",
          "level": 2,
          "index": 2
        },
        {
          "title": "聆听  《闲聊波尔卡》《匈牙利舞曲第五号》《加沃特舞曲》",
          "level": 2,
          "index": 3
        },
        {
          "title": "编创  丰富多彩的舞蹈节奏",
          "level": 2,
          "index": 4
        }
      ]
    },
    {
      "title": "第三单元 七子之歌",
      "level": 1,
      "index": 3,
      "children": [
        {
          "title": "开心一刻  说圆唱圆",
          "level": 2,
          "index": 1
        },
        {
          "title": "唱歌  《七子之歌——澳门》《爷爷的打渔船》",
          "level": 2,
          "index": 2
        },
        {
          "title": "聆听  《阿里山的姑娘》《御风万里》",
          "level": 2,
          "index": 3
        },
        {
          "title": "编创  同心结与漂流瓶",
          "level": 2,
          "index": 4
        }
      ]
    },
    {
      "title": "小舞台 综合活动（一）",
      "level": 1,
      "index": 4,
      "children": [
        {
          "title": "显身手 点歌台",
          "level": 2,
          "index": 1
        }
      ]
    },
    {
      "title": "第四单元 多彩剧苑",
      "level": 1,
      "index": 5,
      "children": [
        {
          "title": "开心一刻  宁波“音乐家”",
          "level": 2,
          "index": 1
        },
        {
          "title": "唱歌  《雪绒花》",
          "level": 2,
          "index": 2
        },
        {
          "title": "聆听  《美妙的小镇》（序曲） 《回忆》",
          "level": 2,
          "index": 3
        },
        {
          "title": "编创  一幅壮锦",
          "level": 2,
          "index": 4
        }
      ]
    },
    {
      "title": "第五单元 欧洲音韵",
      "level": 1,
      "index": 6,
      "children": [
        {
          "title": "开心一刻  欧洲之旅",
          "level": 2,
          "index": 1
        },
        {
          "title": "唱歌  《伦敦德里小调》《摇篮曲》",
          "level": 2,
          "index": 2
        },
        {
          "title": "聆听  《船歌》《幽默曲》",
          "level": 2,
          "index": 3
        },
        {
          "title": "编创  有趣的节奏",
          "level": 2,
          "index": 4
        }
      ]
    },
    {
      "title": "第六单元 依依校园情",
      "level": 1,
      "index": 7,
      "children": [
        {
          "title": "开心一刻  理想",
          "level": 2,
          "index": 1
        },
        {
          "title": "唱歌  《校园的早晨》《男孩女孩》",
          "level": 2,
          "index": 2
        },
        {
          "title": "聆听  《我们走进十月的阳光》《唱给母校的歌》",
          "level": 2,
          "index": 3
        },
        {
          "title": "编创  校园情景",
          "level": 2,
          "index": 4
        }
      ]
    },
    {
      "title": "小舞台 综合活动（二）",
      "level": 1,
      "index": 8,
      "children": [
        {
          "title": "显身手 点歌台",
          "level": 2,
          "index": 1
        }
      ]
    }
  ]
}