{
  "title": "初中艺术教科版九年级下册",
  "xueduan": "初中",
  "nianji": "九年级",
  "xueke": "艺术·舞蹈/影视/戏剧",
  "banben": "教科版",
  "ceci": "下册",
  "is_new": false,
  "chapters": [
    {
      "title": "第1单元 生命如歌",
      "level": 1,
      "index": 1,
      "children": [
        {
          "title": "1 爱的奉献",
          "level": 2,
          "index": 1
        },
        {
          "title": "2 珍惜生命，热爱和平",
          "level": 2,
          "index": 2
        },
        {
          "title": "3 生命在于运动",
          "level": 2,
          "index": 3
        }
      ]
    },
    {
      "title": "第2单元 艺术作品中的建构",
      "level": 1,
      "index": 2,
      "children": [
        {
          "title": "1 流动的建筑",
          "level": 2,
          "index": 1
        },
        {
          "title": "2 立体构成",
          "level": 2,
          "index": 2
        }
      ]
    },
    {
      "title": "第3单元 美洲、非洲民间艺术",
      "level": 1,
      "index": 3,
      "children": [
        {
          "title": "1 美洲、非洲的民间歌曲",
          "level": 2,
          "index": 1
        },
        {
          "title": "2 非洲、拉丁美洲的民间舞蹈",
          "level": 2,
          "index": 2
        },
        {
          "title": "3 神秘奇异的雕塑和面具",
          "level": 2,
          "index": 3
        }
      ]
    },
    {
      "title": "第4单元 多元的现代",
      "level": 1,
      "index": 4,
      "children": [
        {
          "title": "1 从印象主义走向现代派",
          "level": 2,
          "index": 1
        },
        {
          "title": "2 现代舞",
          "level": 2,
          "index": 2
        },
        {
          "title": "3 现代造型艺术",
          "level": 2,
          "index": 3
        }
      ]
    },
    {
      "title": "第5单元 大家动手拍电影",
      "level": 1,
      "index": 5,
      "children": [
        {
          "title": "1 寻找一个故事",
          "level": 2,
          "index": 1
        },
        {
          "title": "2 拍摄",
          "level": 2,
          "index": 2
        },
        {
          "title": "3 后期处理",
          "level": 2,
          "index": 3
        }
      ]
    },
    {
      "title": "第6单元 徜徉在艺术的海洋",
      "level": 1,
      "index": 6,
      "children": [
        {
          "title": "1 毕业美术展",
          "level": 2,
          "index": 1
        },
        {
          "title": "2 毕业联欢会",
          "level": 2,
          "index": 2
        }
      ]
    }
  ]
}