{
  "title": "小学数学苏教版一年级下册",
  "xueduan": "小学",
  "nianji": "一年级",
  "xueke": "数学",
  "banben": "苏教版",
  "ceci": "下册",
  "is_new": false,
  "chapters": [
    {
      "title": "一 20以内的退位减法",
      "level": 1,
      "index": 1,
      "children": [
        {
          "title": "十几减9",
          "level": 2,
          "index": 1
        },
        {
          "title": "练习一",
          "level": 2,
          "index": 2
        },
        {
          "title": "十几减8、7",
          "level": 2,
          "index": 3
        },
        {
          "title": "练习二",
          "level": 2,
          "index": 4
        },
        {
          "title": "十几减6、5、4、3、2",
          "level": 2,
          "index": 5
        },
        {
          "title": "练习三",
          "level": 2,
          "index": 6
        },
        {
          "title": "复习",
          "level": 2,
          "index": 7
        }
      ]
    },
    {
      "title": "二 认识图形（二）",
      "level": 1,
      "index": 2,
      "children": [
        {
          "title": "认识长方形、正方形、三角形和圆",
          "level": 2,
          "index": 1
        },
        {
          "title": "练习四",
          "level": 2,
          "index": 2
        }
      ]
    },
    {
      "title": "三 认识100以内的数",
      "level": 1,
      "index": 3,
      "children": [
        {
          "title": "数的含义",
          "level": 2,
          "index": 1
        },
        {
          "title": "数的读、写",
          "level": 2,
          "index": 2
        },
        {
          "title": "整十数加一位数及相应的减法",
          "level": 2,
          "index": 3
        },
        {
          "title": "练习五",
          "level": 2,
          "index": 4
        },
        {
          "title": "数的顺序",
          "level": 2,
          "index": 5
        },
        {
          "title": "比较数的大小",
          "level": 2,
          "index": 6
        },
        {
          "title": "多些、少些、多得多、少得多",
          "level": 2,
          "index": 7
        },
        {
          "title": "练习六",
          "level": 2,
          "index": 8
        },
        {
          "title": "复习",
          "level": 2,
          "index": 9
        },
        {
          "title": "● 我们认识的数",
          "level": 2,
          "index": 10
        }
      ]
    },
    {
      "title": "四 100以内的加法和减法（一）",
      "level": 1,
      "index": 4,
      "children": [
        {
          "title": "整十数加、减整十数",
          "level": 2,
          "index": 1
        },
        {
          "title": "两位数加整十数、一位数（不进位）",
          "level": 2,
          "index": 2
        },
        {
          "title": "两位数加整十数、一位数（不进位）练习",
          "level": 2,
          "index": 3
        },
        {
          "title": "求被减数的实际问题",
          "level": 2,
          "index": 4
        },
        {
          "title": "练习七",
          "level": 2,
          "index": 5
        },
        {
          "title": "两位数减整十数、一位数（不退位）",
          "level": 2,
          "index": 6
        },
        {
          "title": "两位数减整十数、一位数（不退位）练习",
          "level": 2,
          "index": 7
        },
        {
          "title": "求减数的实际问题",
          "level": 2,
          "index": 8
        },
        {
          "title": "练习八",
          "level": 2,
          "index": 9
        },
        {
          "title": "两位数加、减两位数（不进位、不退位）",
          "level": 2,
          "index": 10
        },
        {
          "title": "求两数相差多少的实际问题",
          "level": 2,
          "index": 11
        },
        {
          "title": "练习九",
          "level": 2,
          "index": 12
        },
        {
          "title": "复习",
          "level": 2,
          "index": 13
        }
      ]
    },
    {
      "title": "五 元、角、分",
      "level": 1,
      "index": 5,
      "children": [
        {
          "title": "认识1元以内的人民币",
          "level": 2,
          "index": 1
        },
        {
          "title": "认识大于1元的人民币",
          "level": 2,
          "index": 2
        },
        {
          "title": "练习十",
          "level": 2,
          "index": 3
        },
        {
          "title": "● 小小商店",
          "level": 2,
          "index": 4
        }
      ]
    },
    {
      "title": "六 100以内的加法和减法（二）",
      "level": 1,
      "index": 6,
      "children": [
        {
          "title": "两位数加一位数（进位）",
          "level": 2,
          "index": 1
        },
        {
          "title": "练习十一",
          "level": 2,
          "index": 2
        },
        {
          "title": "两位数减一位数（退位）",
          "level": 2,
          "index": 3
        },
        {
          "title": "练习十二",
          "level": 2,
          "index": 4
        },
        {
          "title": "两位数加两位数（进位）",
          "level": 2,
          "index": 5
        },
        {
          "title": "练习十三",
          "level": 2,
          "index": 6
        },
        {
          "title": "两位数减两位数（退位）",
          "level": 2,
          "index": 7
        },
        {
          "title": "练习十四",
          "level": 2,
          "index": 8
        },
        {
          "title": "复习",
          "level": 2,
          "index": 9
        }
      ]
    },
    {
      "title": "七 期末复习",
      "level": 1,
      "index": 7,
      "children": [
        {
          "title": "认数、认图形和认识人民币复习",
          "level": 2,
          "index": 1
        },
        {
          "title": "100以内的加、减法（口算）及其 应用复习",
          "level": 2,
          "index": 2
        },
        {
          "title": "100以内的加、减法（笔算）及其应用复习",
          "level": 2,
          "index": 3
        },
        {
          "title": "加、减法实际问题复习",
          "level": 2,
          "index": 4
        }
      ]
    }
  ]
}